ekho/__init__.py
ekho/scraper.py
ekho_scraper_client-0.1.1.dist-info/licenses/LICENSE
ekho_scraper_client-0.1.1.dist-info/METADATA
ekho_scraper_client-0.1.1.dist-info/WHEEL
ekho_scraper_client-0.1.1.dist-info/top_level.txt
ekho_scraper_client-0.1.1.dist-info/RECORD
