Metadata-Version: 2.4
Name: ekho-scraper-client
Version: 0.1.1
Summary: A Python client for the Ekho scraping service
Author-email: Your Name <you@example.com>
License: MIT
Classifier: Programming Language :: Python :: 3
Classifier: License :: OSI Approved :: MIT License
Classifier: Operating System :: OS Independent
Requires-Python: >=3.7
License-File: LICENSE
Requires-Dist: requests>=2.0
Dynamic: license-file
